align4d/__init__.py
align4d/align.py
align4d/align4d.py
align4d/cpp/align.cpp
align4d/cpp/align.h
align4d/cpp/align4d_cpython_extension.cpp
align4d/cpp/msa.cpp
align4d/cpp/msa.h
align4d/cpp/postprocess.cpp
align4d/cpp/postprocess.h
align4d/cpp/preprocess.cpp
align4d/cpp/preprocess.h
align4d/cpp/setup.py
align4d-1.2.3.dist-info/WHEEL
align4d-1.2.3.dist-info/METADATA
align4d-1.2.3.dist-info/RECORD
