Metadata-Version: 2.1
Name: align4d
Version: 1.2.3
Summary: align4d: Multi-sequence alignment tools for aligning ASR and Speaker Diarization result
Author-email: Peilin Wu <pwu54@emory.edu>
Requires-Python: >=3.10
Classifier: Programming Language :: Python :: 3
Classifier: License :: OSI Approved :: Apache Software License
Classifier: Operating System :: Microsoft :: Windows :: Windows 10
Classifier: Operating System :: Microsoft :: Windows :: Windows 11
Classifier: Operating System :: MacOS :: MacOS X
Classifier: Operating System :: POSIX :: Linux
Project-URL: Bug Tracker, https://github.com/emorynlp/align4d/issues
Project-URL: Homepage, https://github.com/emorynlp/align4d
